collective.campaignmonitor-2.0.0-py3.11-nspkg.pth
collective/campaignmonitor/__init__.py
collective/campaignmonitor/configure.zcml
collective/campaignmonitor/connection.py
collective/campaignmonitor/interfaces.py
collective/campaignmonitor/permissions.zcml
collective/campaignmonitor/setuphandlers.py
collective/campaignmonitor/testing.py
collective/campaignmonitor/upgrades.py
collective/campaignmonitor/upgrades.zcml
collective/campaignmonitor/browser/__init__.py
collective/campaignmonitor/browser/configure.zcml
collective/campaignmonitor/browser/controlpanel.pt
collective/campaignmonitor/browser/controlpanel.py
collective/campaignmonitor/browser/subscription.py
collective/campaignmonitor/browser/static/.gitkeep
collective/campaignmonitor/locales/README.rst
collective/campaignmonitor/locales/__init__.py
collective/campaignmonitor/locales/collective.campaignmonitor.pot
collective/campaignmonitor/locales/update.py
collective/campaignmonitor/locales/update.sh
collective/campaignmonitor/locales/en/LC_MESSAGES/collective.campaignmonitor.po
collective/campaignmonitor/locales/es/LC_MESSAGES/collective.campaignmonitor.po
collective/campaignmonitor/locales/eu/LC_MESSAGES/collective.campaignmonitor.po
collective/campaignmonitor/profiles/default/browserlayer.xml
collective/campaignmonitor/profiles/default/catalog.xml
collective/campaignmonitor/profiles/default/controlpanel.xml
collective/campaignmonitor/profiles/default/metadata.xml
collective/campaignmonitor/profiles/default/registry.xml
collective/campaignmonitor/profiles/default/rolemap.xml
collective/campaignmonitor/profiles/uninstall/browserlayer.xml
collective/campaignmonitor/profiles/uninstall/controlpanel.xml
collective/campaignmonitor/profiles/uninstall/registry.xml
collective/campaignmonitor/tests/__init__.py
collective/campaignmonitor/tests/test_setup.py
collective/campaignmonitor/tests/test_upgrade_step_1001.py
collective/campaignmonitor/tests/test_vocab_campaign_monitor_clients_vocabulary.py
collective_campaignmonitor-2.0.0.dist-info/licenses/LICENSE.GPL
collective_campaignmonitor-2.0.0.dist-info/licenses/LICENSE.rst
collective_campaignmonitor-2.0.0.dist-info/METADATA
collective_campaignmonitor-2.0.0.dist-info/WHEEL
collective_campaignmonitor-2.0.0.dist-info/entry_points.txt
collective_campaignmonitor-2.0.0.dist-info/namespace_packages.txt
collective_campaignmonitor-2.0.0.dist-info/top_level.txt
collective_campaignmonitor-2.0.0.dist-info/RECORD
