Metadata-Version: 2.4
Name: collective.campaignmonitor
Version: 2.0.0
Summary: CampaignMonitor integration for Plone
Home-page: https://github.com/collective/collective.campaignmonitor
Author: Mikel Larreategi
Author-email: mlarreategi@codesyntax.com
License: GPL version 2
Project-URL: PyPI, https://pypi.python.org/pypi/collective.campaignmonitor
Project-URL: Source, https://github.com/collective/collective.campaignmonitor
Project-URL: Tracker, https://github.com/collective/collective.campaignmonitor/issues
Keywords: Python Plone
Classifier: Environment :: Web Environment
Classifier: Framework :: Plone
Classifier: Framework :: Plone :: Addon
Classifier: Framework :: Plone :: 6.0
Classifier: Framework :: Plone :: 6.1
Classifier: Programming Language :: Python
Classifier: Programming Language :: Python :: 3.9
Classifier: Programming Language :: Python :: 3.10
Classifier: Programming Language :: Python :: 3.11
Classifier: Programming Language :: Python :: 3.12
Classifier: Programming Language :: Python :: 3.13
Classifier: Operating System :: OS Independent
Classifier: License :: OSI Approved :: GNU General Public License v2 (GPLv2)
Classifier: Development Status :: 5 - Production/Stable
Requires-Python: >=3.9
License-File: LICENSE.GPL
License-File: LICENSE.rst
Requires-Dist: setuptools
Requires-Dist: plone.api>=1.8.4
Requires-Dist: createsend>=8.0.0
Requires-Dist: Products.CMFPlone
Requires-Dist: Zope
Requires-Dist: z3c.form
Requires-Dist: plone.app.registry
Requires-Dist: plone.app.upgrade
Requires-Dist: Products.GenericSetup
Requires-Dist: plone.protect
Provides-Extra: test
Requires-Dist: plone.app.testing; extra == "test"
Requires-Dist: plone.testing>=5.0.0; extra == "test"
Requires-Dist: plone.app.contenttypes; extra == "test"
Requires-Dist: plone.app.robotframework[debug]; extra == "test"
Requires-Dist: plone.base; extra == "test"
Requires-Dist: plone.browserlayer; extra == "test"
Requires-Dist: zope.schema; extra == "test"
Requires-Dist: zope.component; extra == "test"
Dynamic: author
Dynamic: author-email
Dynamic: classifier
Dynamic: description
Dynamic: home-page
Dynamic: keywords
Dynamic: license
Dynamic: license-file
Dynamic: project-url
Dynamic: provides-extra
Dynamic: requires-dist
Dynamic: requires-python
Dynamic: summary
